Metadata-Version: 2.1
Name: trainyourclf
Version: 1.0
Summary: Package to train common Image classifiers on custom data
Home-page: UNKNOWN
Author: Muhammad Rizwan Munawar
Author-email: muhammadrizwanmunawar123@email.com
License: UNKNOWN
Platform: UNKNOWN
License-File: LICENSE
